dssm/__init__.py
dssm/dataset.py
dssm/model.py
dssm/utils.py
dssm/vectorizer.py
dssm-0.1.3.dist-info/LICENSE.txt
dssm-0.1.3.dist-info/METADATA
dssm-0.1.3.dist-info/WHEEL
dssm-0.1.3.dist-info/top_level.txt
dssm-0.1.3.dist-info/RECORD
