Metadata-Version: 2.1
Name: dssm
Version: 0.1.3
Summary: An industrial-grade implementation of DSSM
Home-page: https://github.com/Chiang97912/dssm
Author: Chiang97912
Author-email: chiang97912@gmail.com
License: UNKNOWN
Keywords: dssm semantic-retrieval text-matching
Platform: UNKNOWN
Classifier: Development Status :: 3 - Alpha
Classifier: Intended Audience :: Developers
Classifier: Topic :: Scientific/Engineering :: Artificial Intelligence
Classifier: License :: OSI Approved :: MIT License
Classifier: Programming Language :: Python :: 3.6
License-File: LICENSE.txt
Requires-Dist: torch (>=1.9.0)
Requires-Dist: nltk (>=3.5)
Requires-Dist: numpy (>=1.19.5)
Requires-Dist: scikit-learn (>=0.21.3)
